LICENSE.txt
MANIFEST.in
README.rst
setup.py
scripts/alignSampleToReference.sh
scripts/calculate_snp_distances.py
scripts/call_consensus.py
scripts/collectSampleMetrics.sh
scripts/combineSampleMetrics.sh
scripts/copy_snppipeline_data.py
scripts/create_snp_list.py
scripts/create_snp_matrix.py
scripts/create_snp_reference_seq.py
scripts/mergeVcf.sh
scripts/prepReference.sh
scripts/prepSamples.sh
scripts/run_snp_pipeline.sh
scripts/snp_filter.py
snp_pipeline.egg-info/PKG-INFO
snp_pipeline.egg-info/SOURCES.txt
snp_pipeline.egg-info/dependency_links.txt
snp_pipeline.egg-info/entry_points.txt
snp_pipeline.egg-info/requires.txt
snp_pipeline.egg-info/top_level.txt
snppipeline/__init__.py
snppipeline/call_consensus.py
snppipeline/call_sites.py
snppipeline/cfsan_snp_pipeline.py
snppipeline/collect_metrics.py
snppipeline/combine_metrics.py
snppipeline/command.py
snppipeline/data.py
snppipeline/distance.py
snppipeline/fastq.py
snppipeline/filter_regions.py
snppipeline/index_ref.py
snppipeline/map_reads.py
snppipeline/merge_sites.py
snppipeline/merge_vcfs.py
snppipeline/pileup.py
snppipeline/purge.py
snppipeline/run.py
snppipeline/snp_matrix.py
snppipeline/snp_reference.py
snppipeline/utils.py
snppipeline/vcf_writer.py
snppipeline/data/agonaExpectedResults/metrics.tsv
snppipeline/data/agonaExpectedResults/referenceSNP.fasta
snppipeline/data/agonaExpectedResults/referenceSNP_preserved.fasta
snppipeline/data/agonaExpectedResults/snp_distance_matrix.tsv
snppipeline/data/agonaExpectedResults/snp_distance_matrix_preserved.tsv
snppipeline/data/agonaExpectedResults/snp_distance_pairwise.tsv
snppipeline/data/agonaExpectedResults/snplist.txt
snppipeline/data/agonaExpectedResults/snplist_preserved.txt
snppipeline/data/agonaExpectedResults/snpma.fasta
snppipeline/data/agonaExpectedResults/snpma.vcf
snppipeline/data/agonaExpectedResults/snpma_preserved.fasta
snppipeline/data/agonaExpectedResults/snpma_preserved.vcf
snppipeline/data/agonaExpectedResults/samples/ERR178926/consensus.fasta
snppipeline/data/agonaExpectedResults/samples/ERR178926/var.flt.vcf
snppipeline/data/agonaExpectedResults/samples/ERR178929/consensus.fasta
snppipeline/data/agonaExpectedResults/samples/ERR178929/var.flt.vcf
