Metadata-Version: 1.1
Name: snp-pipeline
Version: 2.2.0
Summary: Script and functions for SNP matrix construction
Home-page: https://github.com/CFSAN-Biostatistics/snp-pipeline
Author: Hugh A. Rand
Author-email: hugh.rand@fda.hhs.gov
License: BSD
Keywords: bioinformatics,NGS,SNP
Platform: UNKNOWN
Classifier: Development Status :: 5 - Production/Stable
Classifier: Environment :: Console
Classifier: Intended Audience :: Science/Research
Classifier: License :: OSI Approved :: BSD License
Classifier: Natural Language :: English
Classifier: Operating System :: POSIX :: Linux
Classifier: Programming Language :: Python
Classifier: Topic :: Scientific/Engineering :: Bio-Informatics
